{
  "m_Version": 12,
  "DisplayName": "SNAFU SUPPRESSORS",
  "Icon": "Deliver",
  "Color": "FBFCFEFF",
  "InitStockPercent": 75.0,
  "IsExchange": 0,
  "Items": [
    {
      "ClassName": "gcgn_m1garand_muzzle",
      "MaxPriceThreshold": 5500,
      "MinPriceThreshold": 5500,
      "SellPricePercent": 25,
      "MaxStockThreshold": 25,
      "MinStockThreshold": 0,
      "QuantityPercent": 15,
      "SpawnAttachments": [],
      "Variants": []
    },
    {
      "ClassName": "gcgn_m1garand_supp",
      "MaxPriceThreshold": 5500,
      "MinPriceThreshold": 5500,
      "SellPricePercent": 25,
      "MaxStockThreshold": 25,
      "MinStockThreshold": 0,
      "QuantityPercent": 15,
      "SpawnAttachments": [],
      "Variants": []
    },
    {
      "ClassName": "snafu_408_suppressor_t",
      "MaxPriceThreshold": 5500,
      "MinPriceThreshold": 5500,
      "SellPricePercent": 25,
      "MaxStockThreshold": 25,
      "MinStockThreshold": 0,
      "QuantityPercent": 15,
      "SpawnAttachments": [],
      "Variants": []
    },
    {
      "ClassName": "snafu_50bmg_suppressor_b",
      "MaxPriceThreshold": 5500,
      "MinPriceThreshold": 5500,
      "SellPricePercent": 25,
      "MaxStockThreshold": 25,
      "MinStockThreshold": 0,
      "QuantityPercent": 15,
      "SpawnAttachments": [],
      "Variants": []
    },
    {
      "ClassName": "snafu_50bmg_suppressor_m",
      "MaxPriceThreshold": 5500,
      "MinPriceThreshold": 5500,
      "SellPricePercent": 25,
      "MaxStockThreshold": 25,
      "MinStockThreshold": 0,
      "QuantityPercent": 15,
      "SpawnAttachments": [],
      "Variants": []
    },
    {
      "ClassName": "snafu_50bmg_suppressor_s",
      "MaxPriceThreshold": 5500,
      "MinPriceThreshold": 5500,
      "SellPricePercent": 25,
      "MaxStockThreshold": 25,
      "MinStockThreshold": 0,
      "QuantityPercent": 15,
      "SpawnAttachments": [],
      "Variants": []
    },
    {
      "ClassName": "snafu_50bmg_suppressor_u",
      "MaxPriceThreshold": 5500,
      "MinPriceThreshold": 5500,
      "SellPricePercent": 25,
      "MaxStockThreshold": 25,
      "MinStockThreshold": 0,
      "QuantityPercent": 15,
      "SpawnAttachments": [],
      "Variants": []
    },
    {
      "ClassName": "snafu_50bmg_suppressor_w",
      "MaxPriceThreshold": 5500,
      "MinPriceThreshold": 5500,
      "SellPricePercent": 25,
      "MaxStockThreshold": 25,
      "MinStockThreshold": 0,
      "QuantityPercent": 15,
      "SpawnAttachments": [],
      "Variants": []
    },
    {
      "ClassName": "snafu_agram_suppressor_black",
      "MaxPriceThreshold": 5500,
      "MinPriceThreshold": 5500,
      "SellPricePercent": 25,
      "MaxStockThreshold": 25,
      "MinStockThreshold": 0,
      "QuantityPercent": 15,
      "SpawnAttachments": [],
      "Variants": []
    },
    {
      "ClassName": "snafu_ak19muzzel",
      "MaxPriceThreshold": 5500,
      "MinPriceThreshold": 5500,
      "SellPricePercent": 25,
      "MaxStockThreshold": 25,
      "MinStockThreshold": 0,
      "QuantityPercent": 15,
      "SpawnAttachments": [],
      "Variants": []
    },
    {
      "ClassName": "snafu_ak308muzzel",
      "MaxPriceThreshold": 5500,
      "MinPriceThreshold": 5500,
      "SellPricePercent": 25,
      "MaxStockThreshold": 25,
      "MinStockThreshold": 0,
      "QuantityPercent": 15,
      "SpawnAttachments": [],
      "Variants": []
    },
    {
      "ClassName": "snafu_heramuzzelf",
      "MaxPriceThreshold": 5500,
      "MinPriceThreshold": 5500,
      "SellPricePercent": 25,
      "MaxStockThreshold": 25,
      "MinStockThreshold": 0,
      "QuantityPercent": 15,
      "SpawnAttachments": [],
      "Variants": []
    },
    {
      "ClassName": "snafu_lnormalized_suppressor_black",
      "MaxPriceThreshold": 5500,
      "MinPriceThreshold": 5500,
      "SellPricePercent": 25,
      "MaxStockThreshold": 25,
      "MinStockThreshold": 0,
      "QuantityPercent": 15,
      "SpawnAttachments": [],
      "Variants": []
    },
    {
      "ClassName": "snafu_lnormalized_suppressor_green",
      "MaxPriceThreshold": 5500,
      "MinPriceThreshold": 5500,
      "SellPricePercent": 25,
      "MaxStockThreshold": 25,
      "MinStockThreshold": 0,
      "QuantityPercent": 15,
      "SpawnAttachments": [],
      "Variants": []
    },
    {
      "ClassName": "snafu_lstandardized_suppressor_black",
      "MaxPriceThreshold": 5500,
      "MinPriceThreshold": 5500,
      "SellPricePercent": 25,
      "MaxStockThreshold": 25,
      "MinStockThreshold": 0,
      "QuantityPercent": 15,
      "SpawnAttachments": [],
      "Variants": []
    },
    {
      "ClassName": "snafu_lstandardized_suppressor_green",
      "MaxPriceThreshold": 5500,
      "MinPriceThreshold": 5500,
      "SellPricePercent": 25,
      "MaxStockThreshold": 25,
      "MinStockThreshold": 0,
      "QuantityPercent": 15,
      "SpawnAttachments": [],
      "Variants": []
    },
    {
      "ClassName": "snafu_mk47muzzel",
      "MaxPriceThreshold": 5500,
      "MinPriceThreshold": 5500,
      "SellPricePercent": 25,
      "MaxStockThreshold": 25,
      "MinStockThreshold": 0,
      "QuantityPercent": 15,
      "SpawnAttachments": [],
      "Variants": []
    },
    {
      "ClassName": "snafu_mpx_suppressor_black",
      "MaxPriceThreshold": 5500,
      "MinPriceThreshold": 5500,
      "SellPricePercent": 25,
      "MaxStockThreshold": 25,
      "MinStockThreshold": 0,
      "QuantityPercent": 15,
      "SpawnAttachments": [],
      "Variants": []
    },
    {
      "ClassName": "snafu_muzzelff",
      "MaxPriceThreshold": 5500,
      "MinPriceThreshold": 5500,
      "SellPricePercent": 25,
      "MaxStockThreshold": 25,
      "MinStockThreshold": 0,
      "QuantityPercent": 15,
      "SpawnAttachments": [],
      "Variants": []
    },
    {
      "ClassName": "snafu_normalized_suppressor_black",
      "MaxPriceThreshold": 5500,
      "MinPriceThreshold": 5500,
      "SellPricePercent": 25,
      "MaxStockThreshold": 25,
      "MinStockThreshold": 0,
      "QuantityPercent": 15,
      "SpawnAttachments": [],
      "Variants": []
    },
    {
      "ClassName": "snafu_normalized_suppressor_green",
      "MaxPriceThreshold": 5500,
      "MinPriceThreshold": 5500,
      "SellPricePercent": 25,
      "MaxStockThreshold": 25,
      "MinStockThreshold": 0,
      "QuantityPercent": 15,
      "SpawnAttachments": [],
      "Variants": []
    },
    {
      "ClassName": "snafu_scarh_sil_black",
      "MaxPriceThreshold": 5500,
      "MinPriceThreshold": 5500,
      "SellPricePercent": 25,
      "MaxStockThreshold": 25,
      "MinStockThreshold": 0,
      "QuantityPercent": 15,
      "SpawnAttachments": [],
      "Variants": []
    },
    {
      "ClassName": "snafu_scarh_sil_tan",
      "MaxPriceThreshold": 5500,
      "MinPriceThreshold": 5500,
      "SellPricePercent": 25,
      "MaxStockThreshold": 25,
      "MinStockThreshold": 0,
      "QuantityPercent": 15,
      "SpawnAttachments": [],
      "Variants": []
    },
    {
      "ClassName": "snafu_shotgunchoke_black",
      "MaxPriceThreshold": 500,
      "MinPriceThreshold": 500,
      "SellPricePercent": 25,
      "MaxStockThreshold": 25,
      "MinStockThreshold": 0,
      "QuantityPercent": 15,
      "SpawnAttachments": [],
      "Variants": []
    },
    {
      "ClassName": "snafu_shotgunchoke_blue",
      "MaxPriceThreshold": 500,
      "MinPriceThreshold": 500,
      "SellPricePercent": 25,
      "MaxStockThreshold": 25,
      "MinStockThreshold": 0,
      "QuantityPercent": 15,
      "SpawnAttachments": [],
      "Variants": []
    },
    {
      "ClassName": "snafu_shotgunchoke_brown",
      "MaxPriceThreshold": 500,
      "MinPriceThreshold": 500,
      "SellPricePercent": 25,
      "MaxStockThreshold": 25,
      "MinStockThreshold": 0,
      "QuantityPercent": 15,
      "SpawnAttachments": [],
      "Variants": []
    },
    {
      "ClassName": "snafu_shotgunchoke_green",
      "MaxPriceThreshold": 500,
      "MinPriceThreshold": 500,
      "SellPricePercent": 25,
      "MaxStockThreshold": 25,
      "MinStockThreshold": 0,
      "QuantityPercent": 15,
      "SpawnAttachments": [],
      "Variants": []
    },
    {
      "ClassName": "snafu_shotgunchoke_purple",
      "MaxPriceThreshold": 500,
      "MinPriceThreshold": 500,
      "SellPricePercent": 25,
      "MaxStockThreshold": 25,
      "MinStockThreshold": 0,
      "QuantityPercent": 15,
      "SpawnAttachments": [],
      "Variants": []
    },
    {
      "ClassName": "snafu_shotgunchoke_red",
      "MaxPriceThreshold": 500,
      "MinPriceThreshold": 500,
      "SellPricePercent": 25,
      "MaxStockThreshold": 25,
      "MinStockThreshold": 0,
      "QuantityPercent": 15,
      "SpawnAttachments": [],
      "Variants": []
    },
    {
      "ClassName": "snafu_shotgunchoke_tur",
      "MaxPriceThreshold": 500,
      "MinPriceThreshold": 500,
      "SellPricePercent": 25,
      "MaxStockThreshold": 25,
      "MinStockThreshold": 0,
      "QuantityPercent": 15,
      "SpawnAttachments": [],
      "Variants": []
    },
    {
      "ClassName": "snafu_shotgunchoke_yellow",
      "MaxPriceThreshold": 500,
      "MinPriceThreshold": 500,
      "SellPricePercent": 25,
      "MaxStockThreshold": 25,
      "MinStockThreshold": 0,
      "QuantityPercent": 15,
      "SpawnAttachments": [],
      "Variants": []
    },
    {
      "ClassName": "snafu_spmod",
      "MaxPriceThreshold": 5500,
      "MinPriceThreshold": 5500,
      "SellPricePercent": 25,
      "MaxStockThreshold": 25,
      "MinStockThreshold": 0,
      "QuantityPercent": 15,
      "SpawnAttachments": [],
      "Variants": []
    },
    {
      "ClassName": "snafu_sr25_supp",
      "MaxPriceThreshold": 5500,
      "MinPriceThreshold": 5500,
      "SellPricePercent": 25,
      "MaxStockThreshold": 25,
      "MinStockThreshold": 0,
      "QuantityPercent": 15,
      "SpawnAttachments": [],
      "Variants": []
    },
    {
      "ClassName": "snafu_sr3vikhr_supp",
      "MaxPriceThreshold": 5500,
      "MinPriceThreshold": 5500,
      "SellPricePercent": 25,
      "MaxStockThreshold": 25,
      "MinStockThreshold": 0,
      "QuantityPercent": 15,
      "SpawnAttachments": [],
      "Variants": []
    },
    {
      "ClassName": "snafu_standardized_suppressor_black",
      "MaxPriceThreshold": 5500,
      "MinPriceThreshold": 5500,
      "SellPricePercent": 25,
      "MaxStockThreshold": 25,
      "MinStockThreshold": 0,
      "QuantityPercent": 15,
      "SpawnAttachments": [],
      "Variants": []
    },
    {
      "ClassName": "snafu_standardized_suppressor_green",
      "MaxPriceThreshold": 5500,
      "MinPriceThreshold": 5500,
      "SellPricePercent": 25,
      "MaxStockThreshold": 25,
      "MinStockThreshold": 0,
      "QuantityPercent": 15,
      "SpawnAttachments": [],
      "Variants": []
    },
    {
      "ClassName": "snafuar15_spr_sil",
      "MaxPriceThreshold": 5500,
      "MinPriceThreshold": 5500,
      "SellPricePercent": 25,
      "MaxStockThreshold": 25,
      "MinStockThreshold": 0,
      "QuantityPercent": 15,
      "SpawnAttachments": [],
      "Variants": []
    },
    {
      "ClassName": "snafuar15_spr_sqsil",
      "MaxPriceThreshold": 5500,
      "MinPriceThreshold": 5500,
      "SellPricePercent": 25,
      "MaxStockThreshold": 25,
      "MinStockThreshold": 0,
      "QuantityPercent": 15,
      "SpawnAttachments": [],
      "Variants": []
    },
    {
      "ClassName": "snafugevar_suppressor_green",
      "MaxPriceThreshold": 5500,
      "MinPriceThreshold": 5500,
      "SellPricePercent": 25,
      "MaxStockThreshold": 25,
      "MinStockThreshold": 0,
      "QuantityPercent": 15,
      "SpawnAttachments": [],
      "Variants": []
    },
    {
      "ClassName": "snafugevar_suppressor_tan",
      "MaxPriceThreshold": 5500,
      "MinPriceThreshold": 5500,
      "SellPricePercent": 25,
      "MaxStockThreshold": 25,
      "MinStockThreshold": 0,
      "QuantityPercent": 15,
      "SpawnAttachments": [],
      "Variants": []
    },
    {
      "ClassName": "snafukivaari_338_supp",
      "MaxPriceThreshold": 5500,
      "MinPriceThreshold": 5500,
      "SellPricePercent": 25,
      "MaxStockThreshold": 25,
      "MinStockThreshold": 0,
      "QuantityPercent": 15,
      "SpawnAttachments": [],
      "Variants": []
    },
    {
      "ClassName": "sr3_vikhr_supp",
      "MaxPriceThreshold": 5500,
      "MinPriceThreshold": 5500,
      "SellPricePercent": 25,
      "MaxStockThreshold": 25,
      "MinStockThreshold": 0,
      "QuantityPercent": 15,
      "SpawnAttachments": [],
      "Variants": []
    }
  ]
}