<?xml version="1.0" encoding="UTF-8" standalone="yes"?>
<types>
  <type name="Animal_HMG_Bear_Radioactive_T0">
    <nominal>0</nominal>
    <lifetime>1800</lifetime>
    <restock>0</restock>
    <min>0</min>
    <quantmin>-1</quantmin>
    <quantmax>-1</quantmax>
    <cost>100</cost>
    <flags count_in_cargo="0" count_in_hoarder="0" count_in_map="1" count_in_player="0" crafted="0" deloot="0" />
  </type>
  <type name="Animal_HMG_Bear_Radioactive_T1">
    <nominal>0</nominal>
    <lifetime>1800</lifetime>
    <restock>0</restock>
    <min>0</min>
    <quantmin>-1</quantmin>
    <quantmax>-1</quantmax>
    <cost>100</cost>
    <flags count_in_cargo="0" count_in_hoarder="0" count_in_map="1" count_in_player="0" crafted="0" deloot="0" />
  </type>
  <type name="Animal_HMG_Bear_Radioactive_T2">
    <nominal>0</nominal>
    <lifetime>1800</lifetime>
    <restock>0</restock>
    <min>0</min>
    <quantmin>-1</quantmin>
    <quantmax>-1</quantmax>
    <cost>100</cost>
    <flags count_in_cargo="0" count_in_hoarder="0" count_in_map="1" count_in_player="0" crafted="0" deloot="0" />
  </type>
  <type name="Animal_HMG_Bear_Radioactive_T3">
    <nominal>0</nominal>
    <lifetime>1800</lifetime>
    <restock>0</restock>
    <min>0</min>
    <quantmin>-1</quantmin>
    <quantmax>-1</quantmax>
    <cost>100</cost>
    <flags count_in_cargo="0" count_in_hoarder="0" count_in_map="1" count_in_player="0" crafted="0" deloot="0" />
  </type>
  <type name="Animal_HMG_Bear_Radioactive_T4">
    <nominal>0</nominal>
    <lifetime>1800</lifetime>
    <restock>0</restock>
    <min>0</min>
    <quantmin>-1</quantmin>
    <quantmax>-1</quantmax>
    <cost>100</cost>
    <flags count_in_cargo="0" count_in_hoarder="0" count_in_map="1" count_in_player="0" crafted="0" deloot="0" />
  </type>
  <type name="Animal_HMG_Bear_Radioactive_T5">
    <nominal>0</nominal>
    <lifetime>1800</lifetime>
    <restock>0</restock>
    <min>0</min>
    <quantmin>-1</quantmin>
    <quantmax>-1</quantmax>
    <cost>100</cost>
    <flags count_in_cargo="0" count_in_hoarder="0" count_in_map="1" count_in_player="0" crafted="0" deloot="0" />
  </type>
  <type name="Animal_HMG_Bear_Radioactive_Vanilla">
    <nominal>0</nominal>
    <lifetime>1800</lifetime>
    <restock>0</restock>
    <min>0</min>
    <quantmin>-1</quantmin>
    <quantmax>-1</quantmax>
    <cost>100</cost>
    <flags count_in_cargo="0" count_in_hoarder="0" count_in_map="1" count_in_player="0" crafted="0" deloot="0" />
  </type>
  <type name="Animal_HMG_Bear_Toxic_T0">
    <nominal>0</nominal>
    <lifetime>1800</lifetime>
    <restock>0</restock>
    <min>0</min>
    <quantmin>-1</quantmin>
    <quantmax>-1</quantmax>
    <cost>100</cost>
    <flags count_in_cargo="0" count_in_hoarder="0" count_in_map="1" count_in_player="0" crafted="0" deloot="0" />
  </type>
  <type name="Animal_HMG_Bear_Toxic_T1">
    <nominal>0</nominal>
    <lifetime>1800</lifetime>
    <restock>0</restock>
    <min>0</min>
    <quantmin>-1</quantmin>
    <quantmax>-1</quantmax>
    <cost>100</cost>
    <flags count_in_cargo="0" count_in_hoarder="0" count_in_map="1" count_in_player="0" crafted="0" deloot="0" />
  </type>
  <type name="Animal_HMG_Bear_Toxic_T2">
    <nominal>0</nominal>
    <lifetime>1800</lifetime>
    <restock>0</restock>
    <min>0</min>
    <quantmin>-1</quantmin>
    <quantmax>-1</quantmax>
    <cost>100</cost>
    <flags count_in_cargo="0" count_in_hoarder="0" count_in_map="1" count_in_player="0" crafted="0" deloot="0" />
  </type>
  <type name="Animal_HMG_Bear_Toxic_T3">
    <nominal>0</nominal>
    <lifetime>1800</lifetime>
    <restock>0</restock>
    <min>0</min>
    <quantmin>-1</quantmin>
    <quantmax>-1</quantmax>
    <cost>100</cost>
    <flags count_in_cargo="0" count_in_hoarder="0" count_in_map="1" count_in_player="0" crafted="0" deloot="0" />
  </type>
  <type name="Animal_HMG_Bear_Toxic_T4">
    <nominal>0</nominal>
    <lifetime>1800</lifetime>
    <restock>0</restock>
    <min>0</min>
    <quantmin>-1</quantmin>
    <quantmax>-1</quantmax>
    <cost>100</cost>
    <flags count_in_cargo="0" count_in_hoarder="0" count_in_map="1" count_in_player="0" crafted="0" deloot="0" />
  </type>
  <type name="Animal_HMG_Bear_Toxic_T5">
    <nominal>0</nominal>
    <lifetime>1800</lifetime>
    <restock>0</restock>
    <min>0</min>
    <quantmin>-1</quantmin>
    <quantmax>-1</quantmax>
    <cost>100</cost>
    <flags count_in_cargo="0" count_in_hoarder="0" count_in_map="1" count_in_player="0" crafted="0" deloot="0" />
  </type>
  <type name="Animal_HMG_Bear_Toxic_Vanilla">
    <nominal>0</nominal>
    <lifetime>1800</lifetime>
    <restock>0</restock>
    <min>0</min>
    <quantmin>-1</quantmin>
    <quantmax>-1</quantmax>
    <cost>100</cost>
    <flags count_in_cargo="0" count_in_hoarder="0" count_in_map="1" count_in_player="0" crafted="0" deloot="0" />
  </type>
  <type name="ContaminatedBearMeat">
    <nominal>0</nominal>
    <lifetime>28800</lifetime>
    <restock>0</restock>
    <min>0</min>
    <quantmin>-1</quantmin>
    <quantmax>-1</quantmax>
    <cost>100</cost>
    <flags count_in_cargo="0" count_in_hoarder="0" count_in_map="1" count_in_player="0" crafted="1" deloot="0" />
    <category name="tools" />
  </type>
  <type name="HMG_RadioactiveBearT0Pelt">
    <nominal>0</nominal>
    <lifetime>28800</lifetime>
    <restock>0</restock>
    <min>0</min>
    <quantmin>-1</quantmin>
    <quantmax>-1</quantmax>
    <cost>100</cost>
    <flags count_in_cargo="0" count_in_hoarder="0" count_in_map="1" count_in_player="0" crafted="1" deloot="0" />
    <category name="tools" />
  </type>
  <type name="HMG_RadioactiveBearT1Pelt">
    <nominal>0</nominal>
    <lifetime>28800</lifetime>
    <restock>0</restock>
    <min>0</min>
    <quantmin>-1</quantmin>
    <quantmax>-1</quantmax>
    <cost>100</cost>
    <flags count_in_cargo="0" count_in_hoarder="0" count_in_map="1" count_in_player="0" crafted="1" deloot="0" />
    <category name="tools" />
  </type>
  <type name="HMG_RadioactiveBearT2Pelt">
    <nominal>0</nominal>
    <lifetime>28800</lifetime>
    <restock>0</restock>
    <min>0</min>
    <quantmin>-1</quantmin>
    <quantmax>-1</quantmax>
    <cost>100</cost>
    <flags count_in_cargo="0" count_in_hoarder="0" count_in_map="1" count_in_player="0" crafted="1" deloot="0" />
    <category name="tools" />
  </type>
  <type name="HMG_RadioactiveBearT3Pelt">
    <nominal>0</nominal>
    <lifetime>28800</lifetime>
    <restock>0</restock>
    <min>0</min>
    <quantmin>-1</quantmin>
    <quantmax>-1</quantmax>
    <cost>100</cost>
    <flags count_in_cargo="0" count_in_hoarder="0" count_in_map="1" count_in_player="0" crafted="1" deloot="0" />
    <category name="tools" />
  </type>
  <type name="HMG_RadioactiveBearT4Pelt">
    <nominal>0</nominal>
    <lifetime>28800</lifetime>
    <restock>0</restock>
    <min>0</min>
    <quantmin>-1</quantmin>
    <quantmax>-1</quantmax>
    <cost>100</cost>
    <flags count_in_cargo="0" count_in_hoarder="0" count_in_map="1" count_in_player="0" crafted="1" deloot="0" />
    <category name="tools" />
  </type>
  <type name="HMG_RadioactiveBearT5Pelt">
    <nominal>0</nominal>
    <lifetime>28800</lifetime>
    <restock>0</restock>
    <min>0</min>
    <quantmin>-1</quantmin>
    <quantmax>-1</quantmax>
    <cost>100</cost>
    <flags count_in_cargo="0" count_in_hoarder="0" count_in_map="1" count_in_player="0" crafted="1" deloot="0" />
    <category name="tools" />
  </type>
  <type name="HMG_RadioactiveBearVanillaPelt">
    <nominal>0</nominal>
    <lifetime>28800</lifetime>
    <restock>0</restock>
    <min>0</min>
    <quantmin>-1</quantmin>
    <quantmax>-1</quantmax>
    <cost>100</cost>
    <flags count_in_cargo="0" count_in_hoarder="0" count_in_map="1" count_in_player="0" crafted="1" deloot="0" />
    <category name="tools" />
  </type>
  <type name="HMG_ToxicBearT0Pelt">
    <nominal>0</nominal>
    <lifetime>28800</lifetime>
    <restock>0</restock>
    <min>0</min>
    <quantmin>-1</quantmin>
    <quantmax>-1</quantmax>
    <cost>100</cost>
    <flags count_in_cargo="0" count_in_hoarder="0" count_in_map="1" count_in_player="0" crafted="1" deloot="0" />
    <category name="tools" />
  </type>
  <type name="HMG_ToxicBearT1Pelt">
    <nominal>0</nominal>
    <lifetime>28800</lifetime>
    <restock>0</restock>
    <min>0</min>
    <quantmin>-1</quantmin>
    <quantmax>-1</quantmax>
    <cost>100</cost>
    <flags count_in_cargo="0" count_in_hoarder="0" count_in_map="1" count_in_player="0" crafted="1" deloot="0" />
    <category name="tools" />
  </type>
  <type name="HMG_ToxicBearT2Pelt">
    <nominal>0</nominal>
    <lifetime>28800</lifetime>
    <restock>0</restock>
    <min>0</min>
    <quantmin>-1</quantmin>
    <quantmax>-1</quantmax>
    <cost>100</cost>
    <flags count_in_cargo="0" count_in_hoarder="0" count_in_map="1" count_in_player="0" crafted="1" deloot="0" />
    <category name="tools" />
  </type>
  <type name="HMG_ToxicBearT3Pelt">
    <nominal>0</nominal>
    <lifetime>28800</lifetime>
    <restock>0</restock>
    <min>0</min>
    <quantmin>-1</quantmin>
    <quantmax>-1</quantmax>
    <cost>100</cost>
    <flags count_in_cargo="0" count_in_hoarder="0" count_in_map="1" count_in_player="0" crafted="1" deloot="0" />
    <category name="tools" />
  </type>
  <type name="HMG_ToxicBearT4Pelt">
    <nominal>0</nominal>
    <lifetime>28800</lifetime>
    <restock>0</restock>
    <min>0</min>
    <quantmin>-1</quantmin>
    <quantmax>-1</quantmax>
    <cost>100</cost>
    <flags count_in_cargo="0" count_in_hoarder="0" count_in_map="1" count_in_player="0" crafted="1" deloot="0" />
    <category name="tools" />
  </type>
  <type name="HMG_ToxicBearT5Pelt">
    <nominal>0</nominal>
    <lifetime>28800</lifetime>
    <restock>0</restock>
    <min>0</min>
    <quantmin>-1</quantmin>
    <quantmax>-1</quantmax>
    <cost>100</cost>
    <flags count_in_cargo="0" count_in_hoarder="0" count_in_map="1" count_in_player="0" crafted="1" deloot="0" />
    <category name="tools" />
  </type>
  <type name="HMG_ToxicBearVanillaPelt">
    <nominal>0</nominal>
    <lifetime>28800</lifetime>
    <restock>0</restock>
    <min>0</min>
    <quantmin>-1</quantmin>
    <quantmax>-1</quantmax>
    <cost>100</cost>
    <flags count_in_cargo="0" count_in_hoarder="0" count_in_map="1" count_in_player="0" crafted="1" deloot="0" />
    <category name="tools" />
  </type>
</types>