{
    "playerId": "76561198215655829",
    "playerName": "Smeagol",
    "playerIsOnline": 0,
    "surviedTime": 66117.6171875,
    "playerKills": 0,
    "playerDeaths": 2,
    "playerLongestDistance": 0,
    "playerKillsAISurvivor": 29,
    "playerKillsZombie": 339,
    "playerKillsBear": 0,
    "playerKillsWolf": 3,
    "playerKillsWildBoar": 3,
    "playerKillsRedDeer": 4,
    "playerKillsRoeDeer": 4,
    "playerKillsSheep": 1,
    "playerKillsGoat": 0,
    "playerKillsCow": 1,
    "playerKillsPig": 0,
    "playerKillsChicken": 6,
    "playerKillsAnimals": 22,
    "playerKillsNPCs": 390
}