{
  "m_Version": 12,
  "DisplayName": "TACTICAL_FLAVA",
  "MinRequiredReputation": 15000,
  "MaxRequiredReputation": 2147483647,
  "RequiredFaction": "",
  "RequiredCompletedQuestID": -1,
  "TraderIcon": "Trader",
  "Currencies": [
    "expansionbanknotehryvnia",
    "expansiongoldbar"
  ],
  "DisplayCurrencyValue": 1,
  "DisplayCurrencyName": "",
  "Categories": [
    "ADVANCED SCOPES",
    "AMMO",
    "BATTERY",
    "NIGHT VISION",
    "TACTICAL FLAVA ACCESSORIES",
    "TACTICALFLAVA_ATTACMENTS",
    "TACTICALFLAVA_VEST",
    "TACTICALFLAVA_HELMET",
    "TACTICAL FLAVA SUPRESSORS",
    "TACTICALFLAVA_BACKPACK",
    "TACTICALFLAVA_SCOPES",
    "TACTICAL FLAVA MAGS",
    "TACTICALFLAVA_NVG"
  ],
  "Items": {
    "tf_adar2_15": 1,
    "tf_aek999": 1,
    "tf_ak101": 1,
    "tf_ak102": 1,
    "tf_ak103": 1,
    "tf_ak104": 1,
    "tf_ak105": 1,
    "tf_ak105_bullpup": 1,
    "tf_ak74m": 1,
    "tf_akm": 1,
    "tf_akmn": 1,
    "tf_aks74u": 1,
    "tf_fiveseven": 1,
    "tf_m14_dmr": 1,
    "tf_m14_ebr": 1,
    "tf_m14_std": 1,
    "tf_m16a4": 1,
    "tf_m1a_black": 1,
    "tf_m4a1": 1,
    "tf_m4a1_cqbr": 1,
    "tf_makarovpb": 1,
    "tf_mar10": 1,
    "tf_mk47": 1,
    "tf_mk47_cqbr": 1,
    "tf_mp443": 1,
    "tf_ots_12_tiss": 1,
    "tf_ots_14_groza": 1,
    "tf_scar_20_fde": 1,
    "tf_scar_20_shd": 1,
    "tf_scar_h_cqc_fde": 1,
    "tf_scar_h_fde": 1,
    "tf_scar_l_cqc_fde": 1,
    "tf_scar_l_fde": 1,
    "tf_sr25": 1,
    "tf_svch": 1,
    "tf_svch308": 1,
    "tf_vpo136": 1,
    "tf_vpo190": 1
  }
}